graia/amnesia/__init__.py
graia/amnesia/builtins/__init__.py
graia/amnesia/builtins/aiohttp.py
graia/amnesia/builtins/asgi/__init__.py
graia/amnesia/builtins/asgi/__init__.pyi
graia/amnesia/builtins/asgi/asgitypes.py
graia/amnesia/builtins/asgi/common.py
graia/amnesia/builtins/asgi/hypercorn.py
graia/amnesia/builtins/asgi/middleware.py
graia/amnesia/builtins/asgi/uvicorn.py
graia/amnesia/builtins/asgi/winloop.py
graia/amnesia/builtins/httpx.py
graia/amnesia/builtins/memcache.py
graia/amnesia/builtins/sqla/__init__.py
graia/amnesia/builtins/sqla/model.py
graia/amnesia/builtins/sqla/service.py
graia/amnesia/builtins/sqla/types.py
graia/amnesia/builtins/utils.py
graia/amnesia/message/__init__.py
graia/amnesia/message/chain.py
graia/amnesia/message/element.py
graia/amnesia/message/formatter.py
graia/amnesia/utilles.py
graia_amnesia-0.11.5.dist-info/METADATA
graia_amnesia-0.11.5.dist-info/WHEEL
graia_amnesia-0.11.5.dist-info/entry_points.txt
graia_amnesia-0.11.5.dist-info/licenses/LICENSE
graia_amnesia-0.11.5.dist-info/RECORD
