Metadata-Version: 2.1
Name: graia-amnesia
Version: 0.11.5
Summary: a collection of shared components for graia
Author-Email: GreyElaina <GreyElaina@outlook.com>, RF-Tar-Railt <rf_tar_railt@qq.com>
License: MIT
Requires-Python: <4.0,>=3.10
Requires-Dist: launart<1.0.0,>=0.7.0
Requires-Dist: typing-extensions>=4.0.0
Provides-Extra: httpx
Requires-Dist: httpx>=0.26.0; extra == "httpx"
Provides-Extra: aiohttp
Requires-Dist: aiohttp>=3.9.1; extra == "aiohttp"
Provides-Extra: sqla
Requires-Dist: sqlalchemy>=2.0.25; extra == "sqla"
Provides-Extra: hypercorn
Requires-Dist: hypercorn>=0.17.3; extra == "hypercorn"
Provides-Extra: uvicorn
Requires-Dist: uvicorn>=0.35.0; extra == "uvicorn"
Requires-Dist: uvloop>=0.18.0; sys_platform != "win32" and extra == "uvicorn"
Requires-Dist: websockets>=15.0.1; extra == "uvicorn"
Requires-Dist: winloop>=0.3.0; sys_platform == "win32" and extra == "uvicorn"
